rapid_utils/__init__.py
rapid_utils/core.py
rapid_utils-0.0.5.dist-info/METADATA
rapid_utils-0.0.5.dist-info/WHEEL
rapid_utils-0.0.5.dist-info/top_level.txt
rapid_utils-0.0.5.dist-info/RECORD
