Metadata-Version: 2.1
Name: rapid-utils
Version: 0.0.5
Summary: high level functions
Home-page: https://github.com/gnaam/rapid-utils
Author: Namdev Gavle
Author-email: gavlenamdevprabha@gmail.com
License: MIT
Download-URL: https://github.com/gnaam/rapid-utils/archive/v0.0.5.tar.gz
Platform: UNKNOWN
Classifier: License :: OSI Approved :: MIT License
Classifier: Operating System :: OS Independent
Classifier: Programming Language :: Python :: 3
Classifier: Programming Language :: Python :: 3.5
Requires-Dist: requests (>=2.22.0)
